{
  "generatedBy": "Noah-AI",
  "schema": 1,
  "lastDeployment": {
    "deploymentId": "dpl_7GL8FeFdYUUoSRvQhXpqrHQwQVLQ",
    "platform": "vercel",
    "commit": "6966999d818ebfc50bddc124d174d36ae27923fe",
    "url": "https://my-portifolio-rouge-three.vercel.app",
    "status": "success",
    "deployedAt": "2026-06-25T06:36:50.697Z"
  },
  "lastSuccessfulDeployment": {
    "deploymentId": "dpl_7GL8FeFdYUUoSRvQhXpqrHQwQVLQ",
    "platform": "vercel",
    "commit": "6966999d818ebfc50bddc124d174d36ae27923fe",
    "url": "https://my-portifolio-rouge-three.vercel.app",
    "deployedAt": "2026-06-25T06:36:50.697Z"
  }
}
